pymchain/__init__.py
pymchain/markov_chains.py
utils/__init__.py
utils/generator_utils.py
pymchain-0.1.dist-info/METADATA
pymchain-0.1.dist-info/WHEEL
pymchain-0.1.dist-info/top_level.txt
pymchain-0.1.dist-info/RECORD
